bazpy/__init__.py
bazpy/decorators.py
bazpy/dotdict.py
bazpy/print.py
bazpy/random.py
bazpy/utc.py
bazpy/testing/testbase.py
bazpy/testing/testbase_async.py
bazpy-0.0.12.dist-info/LICENSE
bazpy-0.0.12.dist-info/METADATA
bazpy-0.0.12.dist-info/WHEEL
bazpy-0.0.12.dist-info/top_level.txt
bazpy-0.0.12.dist-info/RECORD
